langchain_triggers/__init__.py
langchain_triggers/app.py
langchain_triggers/core.py
langchain_triggers/cron_manager.py
langchain_triggers/decorators.py
langchain_triggers/auth/__init__.py
langchain_triggers/auth/slack_hmac.py
langchain_triggers/database/__init__.py
langchain_triggers/database/interface.py
langchain_triggers/database/supabase.py
langchain_triggers/triggers/__init__.py
langchain_triggers/triggers/cron_trigger.py
langchain_trigger_server-0.31.dist-info/METADATA
langchain_trigger_server-0.31.dist-info/WHEEL
langchain_trigger_server-0.31.dist-info/RECORD
