Metadata-Version: 2.4
Name: langchain-trigger-server
Version: 0.31
Summary: Generic event-driven triggers framework
Project-URL: Homepage, https://github.com/langchain-ai/open-agent-platform
Project-URL: Repository, https://github.com/langchain-ai/open-agent-platform
Author: Open Agent Platform Team
License: MIT
Keywords: agents,events,triggers,webhooks
Classifier: Development Status :: 3 - Alpha
Classifier: Intended Audience :: Developers
Classifier: License :: OSI Approved :: MIT License
Classifier: Programming Language :: Python :: 3
Classifier: Programming Language :: Python :: 3.11
Classifier: Programming Language :: Python :: 3.12
Requires-Python: >=3.11
Requires-Dist: apscheduler>=3.10.0
Requires-Dist: croniter>=1.4.0
Requires-Dist: cryptography>=3.0.0
Requires-Dist: fastapi>=0.100.0
Requires-Dist: httpx>=0.24.0
Requires-Dist: langchain-auth>=0.0.1
Requires-Dist: langgraph-sdk>=0.2.6
Requires-Dist: pydantic>=2.0.0
Requires-Dist: python-jose[cryptography]>=3.3.0
Requires-Dist: python-multipart>=0.0.6
Requires-Dist: supabase>=2.0.0
Requires-Dist: uvicorn[standard]>=0.20.0
Provides-Extra: dev
Requires-Dist: black>=23.0.0; extra == 'dev'
Requires-Dist: mypy>=1.0.0; extra == 'dev'
Requires-Dist: pytest-asyncio>=0.21.0; extra == 'dev'
Requires-Dist: pytest>=7.0.0; extra == 'dev'
Requires-Dist: ruff>=0.1.0; extra == 'dev'
